[{"line":1,"elements":[{"start_timestamp":"2023-08-16T19:56:30.682Z","before":[{"result":{"duration":6604287000,"status":"passed"},"match":{"location":"heal.com.stepDefinitions.BeforeScenario.beforeChromeScenario(io.cucumber.java.Scenario)"}}],"line":13,"name":"Verify User Login with Valid Credentials","description":"","id":"heal-log-in-feature;verify-user-login-with-valid-credentials;;2","type":"scenario","keyword":"Scenario Outline","steps":[{"result":{"duration":5633628200,"status":"passed"},"line":4,"name":"User in on the CVS homepage","match":{"location":"heal.com.stepDefinitions.com_Heal_Login_stepDefinitions.user_in_on_the_cvs_homepage()"},"keyword":"Given "},{"result":{"duration":1041100,"status":"passed"},"line":5,"name":"I click on dropdown sign on","match":{"location":"heal.com.stepDefinitions.com_Heal_Login_stepDefinitions.i_click_on_dropdown_sign_on()"},"keyword":"When "},{"result":{"duration":1000600,"status":"passed"},"line":6,"name":"I click on sign in button","match":{"location":"heal.com.stepDefinitions.com_Heal_Login_stepDefinitions.i_click_on_sign_in_button()"},"keyword":"And "},{"result":{"duration":10543400,"status":"passed"},"line":7,"name":"I enter valid qa.barbie.oppenheimer@gmail.com","match":{"location":"heal.com.stepDefinitions.com_Heal_Login_stepDefinitions.i_enter_valid_qa_barbie_oppenheimer_gmail_com()"},"keyword":"Then "},{"result":{"duration":1001600,"status":"passed"},"line":8,"name":"click continue","match":{"location":"heal.com.stepDefinitions.com_Heal_Login_stepDefinitions.click_continue()"},"keyword":"And "},{"result":{"duration":1000200,"status":"passed"},"line":9,"name":"I enter valid Success2023","match":{"location":"heal.com.stepDefinitions.com_Heal_Login_stepDefinitions.i_enter_valid_success2023()"},"keyword":"And "},{"result":{"status":"passed"},"line":10,"name":"I click submit button","match":{"location":"heal.com.stepDefinitions.com_Heal_Login_stepDefinitions.i_click_submit_button()"},"keyword":"Then "}],"tags":[{"name":"@sanity"},{"name":"@chrome"}]}],"name":"Heal Log IN Feature","description":"","id":"heal-log-in-feature","keyword":"Feature","uri":"file:src/test/resources/Features/heal_Login.feature","tags":[]}]